{
  "generated_from": "@modelcontextprotocol/server 2.0.0-beta.4 wire registration",
  "tool_count": 88,
  "tools_list_bytes": 517143,
  "budgets": {
    "tools_list_bytes": 524288,
    "per_tool_bytes": 65536
  },
  "tools": [
    {
      "name": "address_name",
      "bytes": 1133,
      "input_schema_bytes": 401,
      "output_schema_bytes": 313
    },
    {
      "name": "analyze_function",
      "bytes": 8935,
      "input_schema_bytes": 2037,
      "output_schema_bytes": 6421
    },
    {
      "name": "analyze_javascript_application",
      "bytes": 17446,
      "input_schema_bytes": 2633,
      "output_schema_bytes": 14172
    },
    {
      "name": "analyze_swift_types",
      "bytes": 1321,
      "input_schema_bytes": 62,
      "output_schema_bytes": 852
    },
    {
      "name": "analyze_web_bundle",
      "bytes": 14276,
      "input_schema_bytes": 6550,
      "output_schema_bytes": 7221
    },
    {
      "name": "batch_decompile",
      "bytes": 10638,
      "input_schema_bytes": 226,
      "output_schema_bytes": 10011
    },
    {
      "name": "binary_overview",
      "bytes": 1620,
      "input_schema_bytes": 250,
      "output_schema_bytes": 954
    },
    {
      "name": "binary_session",
      "bytes": 11822,
      "input_schema_bytes": 367,
      "output_schema_bytes": 10955
    },
    {
      "name": "build_call_path",
      "bytes": 10235,
      "input_schema_bytes": 6850,
      "output_schema_bytes": 2913
    },
    {
      "name": "capture_process_scenario",
      "bytes": 19830,
      "input_schema_bytes": 10303,
      "output_schema_bytes": 8773
    },
    {
      "name": "capture_web_screenshot",
      "bytes": 5389,
      "input_schema_bytes": 771,
      "output_schema_bytes": 4182
    },
    {
      "name": "close_binary",
      "bytes": 1073,
      "input_schema_bytes": 214,
      "output_schema_bytes": 379
    },
    {
      "name": "comment",
      "bytes": 1082,
      "input_schema_bytes": 401,
      "output_schema_bytes": 313
    },
    {
      "name": "compare_application_versions",
      "bytes": 24888,
      "input_schema_bytes": 9296,
      "output_schema_bytes": 15024
    },
    {
      "name": "compare_artifacts",
      "bytes": 3869,
      "input_schema_bytes": 759,
      "output_schema_bytes": 2625
    },
    {
      "name": "compare_bundles",
      "bytes": 4169,
      "input_schema_bytes": 928,
      "output_schema_bytes": 2742
    },
    {
      "name": "compare_functions",
      "bytes": 4356,
      "input_schema_bytes": 725,
      "output_schema_bytes": 3139
    },
    {
      "name": "compare_managed_members",
      "bytes": 7583,
      "input_schema_bytes": 960,
      "output_schema_bytes": 6099
    },
    {
      "name": "compare_process_captures",
      "bytes": 3311,
      "input_schema_bytes": 565,
      "output_schema_bytes": 2161
    },
    {
      "name": "compare_web_captures",
      "bytes": 29996,
      "input_schema_bytes": 27683,
      "output_schema_bytes": 1873
    },
    {
      "name": "compare_web_screenshots",
      "bytes": 3351,
      "input_schema_bytes": 1412,
      "output_schema_bytes": 1546
    },
    {
      "name": "correlate_static_and_runtime",
      "bytes": 12426,
      "input_schema_bytes": 8307,
      "output_schema_bytes": 3626
    },
    {
      "name": "current_address",
      "bytes": 938,
      "input_schema_bytes": 282,
      "output_schema_bytes": 285
    },
    {
      "name": "current_document",
      "bytes": 842,
      "input_schema_bytes": 219,
      "output_schema_bytes": 285
    },
    {
      "name": "current_procedure",
      "bytes": 952,
      "input_schema_bytes": 282,
      "output_schema_bytes": 285
    },
    {
      "name": "demangle_swift",
      "bytes": 2276,
      "input_schema_bytes": 221,
      "output_schema_bytes": 1717
    },
    {
      "name": "discover_webmcp_tools",
      "bytes": 6797,
      "input_schema_bytes": 1087,
      "output_schema_bytes": 5306
    },
    {
      "name": "export_evidence_bundle",
      "bytes": 11008,
      "input_schema_bytes": 196,
      "output_schema_bytes": 10384
    },
    {
      "name": "extract_artifact",
      "bytes": 6212,
      "input_schema_bytes": 1321,
      "output_schema_bytes": 4499
    },
    {
      "name": "find_changed_behavior",
      "bytes": 12036,
      "input_schema_bytes": 8540,
      "output_schema_bytes": 2968
    },
    {
      "name": "find_xrefs_to_name",
      "bytes": 1346,
      "input_schema_bytes": 128,
      "output_schema_bytes": 763
    },
    {
      "name": "get_call_graph",
      "bytes": 10619,
      "input_schema_bytes": 361,
      "output_schema_bytes": 9786
    },
    {
      "name": "get_objc_classes",
      "bytes": 1141,
      "input_schema_bytes": 127,
      "output_schema_bytes": 606
    },
    {
      "name": "get_objc_protocols",
      "bytes": 1079,
      "input_schema_bytes": 62,
      "output_schema_bytes": 610
    },
    {
      "name": "goto_address",
      "bytes": 1094,
      "input_schema_bytes": 424,
      "output_schema_bytes": 285
    },
    {
      "name": "import_evidence_bundle",
      "bytes": 882,
      "input_schema_bytes": 142,
      "output_schema_bytes": 321
    },
    {
      "name": "inline_comment",
      "bytes": 1064,
      "input_schema_bytes": 401,
      "output_schema_bytes": 313
    },
    {
      "name": "inspect_electron_page",
      "bytes": 9514,
      "input_schema_bytes": 1936,
      "output_schema_bytes": 7118
    },
    {
      "name": "inspect_macho",
      "bytes": 7672,
      "input_schema_bytes": 62,
      "output_schema_bytes": 7237
    },
    {
      "name": "inspect_managed_artifact",
      "bytes": 11489,
      "input_schema_bytes": 1251,
      "output_schema_bytes": 9754
    },
    {
      "name": "inspect_managed_members",
      "bytes": 13925,
      "input_schema_bytes": 2048,
      "output_schema_bytes": 11387
    },
    {
      "name": "inspect_managed_native_boundaries",
      "bytes": 9704,
      "input_schema_bytes": 1267,
      "output_schema_bytes": 7912
    },
    {
      "name": "inspect_plist",
      "bytes": 2769,
      "input_schema_bytes": 189,
      "output_schema_bytes": 2206
    },
    {
      "name": "inspect_signature",
      "bytes": 2793,
      "input_schema_bytes": 62,
      "output_schema_bytes": 2366
    },
    {
      "name": "inspect_web_page",
      "bytes": 21829,
      "input_schema_bytes": 5042,
      "output_schema_bytes": 16277
    },
    {
      "name": "inventory_artifact",
      "bytes": 9791,
      "input_schema_bytes": 1885,
      "output_schema_bytes": 7519
    },
    {
      "name": "list_architectures",
      "bytes": 2555,
      "input_schema_bytes": 62,
      "output_schema_bytes": 2160
    },
    {
      "name": "list_bookmarks",
      "bytes": 1091,
      "input_schema_bytes": 282,
      "output_schema_bytes": 437
    },
    {
      "name": "list_browser_targets",
      "bytes": 2950,
      "input_schema_bytes": 658,
      "output_schema_bytes": 1844
    },
    {
      "name": "list_documents",
      "bytes": 883,
      "input_schema_bytes": 219,
      "output_schema_bytes": 310
    },
    {
      "name": "list_electron_targets",
      "bytes": 2869,
      "input_schema_bytes": 636,
      "output_schema_bytes": 1810
    },
    {
      "name": "list_names",
      "bytes": 2786,
      "input_schema_bytes": 594,
      "output_schema_bytes": 1762
    },
    {
      "name": "list_procedures",
      "bytes": 2683,
      "input_schema_bytes": 475,
      "output_schema_bytes": 1762
    },
    {
      "name": "list_segments",
      "bytes": 2656,
      "input_schema_bytes": 282,
      "output_schema_bytes": 1967
    },
    {
      "name": "list_strings",
      "bytes": 2781,
      "input_schema_bytes": 594,
      "output_schema_bytes": 1762
    },
    {
      "name": "list_unknowns",
      "bytes": 4279,
      "input_schema_bytes": 358,
      "output_schema_bytes": 3512
    },
    {
      "name": "next_address",
      "bytes": 1039,
      "input_schema_bytes": 401,
      "output_schema_bytes": 285
    },
    {
      "name": "observe_web_session",
      "bytes": 5976,
      "input_schema_bytes": 765,
      "output_schema_bytes": 4746
    },
    {
      "name": "open_binary",
      "bytes": 1702,
      "input_schema_bytes": 386,
      "output_schema_bytes": 696
    },
    {
      "name": "plan_managed_runtime_correlation",
      "bytes": 7556,
      "input_schema_bytes": 2128,
      "output_schema_bytes": 4768
    },
    {
      "name": "prev_address",
      "bytes": 1045,
      "input_schema_bytes": 401,
      "output_schema_bytes": 285
    },
    {
      "name": "procedure_address",
      "bytes": 1082,
      "input_schema_bytes": 383,
      "output_schema_bytes": 285
    },
    {
      "name": "procedure_assembly",
      "bytes": 1096,
      "input_schema_bytes": 383,
      "output_schema_bytes": 285
    },
    {
      "name": "procedure_callees",
      "bytes": 1121,
      "input_schema_bytes": 383,
      "output_schema_bytes": 310
    },
    {
      "name": "procedure_callers",
      "bytes": 1085,
      "input_schema_bytes": 383,
      "output_schema_bytes": 310
    },
    {
      "name": "procedure_info",
      "bytes": 1982,
      "input_schema_bytes": 383,
      "output_schema_bytes": 1216
    },
    {
      "name": "procedure_pseudo_code",
      "bytes": 1172,
      "input_schema_bytes": 383,
      "output_schema_bytes": 313
    },
    {
      "name": "procedure_references",
      "bytes": 4192,
      "input_schema_bytes": 798,
      "output_schema_bytes": 2927
    },
    {
      "name": "reconcile_javascript_runtime",
      "bytes": 27214,
      "input_schema_bytes": 8993,
      "output_schema_bytes": 17696
    },
    {
      "name": "record_unknown",
      "bytes": 6527,
      "input_schema_bytes": 2646,
      "output_schema_bytes": 3487
    },
    {
      "name": "resolve_containing_procedure",
      "bytes": 2185,
      "input_schema_bytes": 424,
      "output_schema_bytes": 1280
    },
    {
      "name": "run_controlled_replay",
      "bytes": 19234,
      "input_schema_bytes": 5922,
      "output_schema_bytes": 12725
    },
    {
      "name": "search_procedures",
      "bytes": 2215,
      "input_schema_bytes": 812,
      "output_schema_bytes": 941
    },
    {
      "name": "search_strings",
      "bytes": 2224,
      "input_schema_bytes": 812,
      "output_schema_bytes": 941
    },
    {
      "name": "set_address_name",
      "bytes": 1141,
      "input_schema_bytes": 478,
      "output_schema_bytes": 286
    },
    {
      "name": "set_addresses_names",
      "bytes": 1175,
      "input_schema_bytes": 427,
      "output_schema_bytes": 361
    },
    {
      "name": "set_bookmark",
      "bytes": 1118,
      "input_schema_bytes": 471,
      "output_schema_bytes": 286
    },
    {
      "name": "set_comment",
      "bytes": 1148,
      "input_schema_bytes": 487,
      "output_schema_bytes": 286
    },
    {
      "name": "set_current_document",
      "bytes": 1003,
      "input_schema_bytes": 298,
      "output_schema_bytes": 285
    },
    {
      "name": "set_inline_comment",
      "bytes": 1142,
      "input_schema_bytes": 487,
      "output_schema_bytes": 286
    },
    {
      "name": "swift_classes",
      "bytes": 1135,
      "input_schema_bytes": 127,
      "output_schema_bytes": 606
    },
    {
      "name": "trace_application_feature",
      "bytes": 24958,
      "input_schema_bytes": 8688,
      "output_schema_bytes": 15739
    },
    {
      "name": "trace_feature",
      "bytes": 3340,
      "input_schema_bytes": 555,
      "output_schema_bytes": 2299
    },
    {
      "name": "unset_bookmark",
      "bytes": 1055,
      "input_schema_bytes": 424,
      "output_schema_bytes": 286
    },
    {
      "name": "update_unknown",
      "bytes": 7572,
      "input_schema_bytes": 3696,
      "output_schema_bytes": 3487
    },
    {
      "name": "verify_reconstruction",
      "bytes": 6161,
      "input_schema_bytes": 2455,
      "output_schema_bytes": 3212
    },
    {
      "name": "verify_unknown_resolution",
      "bytes": 4283,
      "input_schema_bytes": 177,
      "output_schema_bytes": 3668
    },
    {
      "name": "xrefs",
      "bytes": 1112,
      "input_schema_bytes": 401,
      "output_schema_bytes": 310
    }
  ]
}
